scaks/__init__.py
scaks/compatutil.py
scaks/functions.py
scaks/mpicommons.py
scaks/correctors/__init__.py
scaks/correctors/corrector_base.py
scaks/correctors/thermodynamic_corrector.py
scaks/database/__init__.py
scaks/database/elements_data.py
scaks/database/lattice_data.py
scaks/database/thermo_data.py
scaks/descriptors/__init__.py
scaks/descriptors/component_descriptors.py
scaks/descriptors/descriptors.py
scaks/errors/__init__.py
scaks/errors/error.py
scaks/models/__init__.py
scaks/models/kinetic_model.py
scaks/models/kmc_model.py
scaks/models/micro_kinetic_model.py
scaks/parsers/__init__.py
scaks/parsers/absolute_energy_parser.py
scaks/parsers/kmc_parser.py
scaks/parsers/parser_base.py
scaks/parsers/relative_energy_parser.py
scaks/parsers/rxn_parser.py
scaks/plotters/__init__.py
scaks/plotters/energy_profile_plotter.py
scaks/plotters/plotter_base.py
scaks/plugins/__init__.py
scaks/plugins/analysis.py
scaks/plugins/hybrid_methods.py
scaks/plugins/metaclasses.py
scaks/solvers/__init__.py
scaks/solvers/kmc_solver.py
scaks/solvers/mean_field_solver.py
scaks/solvers/rootfinding_iterators.py
scaks/solvers/solver_base.py
scaks/solvers/steady_state_solver.py
scaks/solvers/kmc_plugins/__init__.py
scaks/solvers/kmc_plugins/coverages_analysis.py
scaks/solvers/kmc_plugins/event_analysis.py
scaks/solvers/kmc_plugins/frequency_analysis.py
scaks/solvers/kmc_plugins/kmc_functions.py
scaks/solvers/kmc_plugins/tof_analysis.py
scaks/solvers/kmc_plugins/plugin_backends/__init__.py
scaks/solvers/kmc_plugins/plugin_backends/kmc_functions.py
scaks/tests/__init__.py
scaks/tests/test_all.py
scaks/tests/correctors/__init__.py
scaks/tests/correctors/correctors_tests.py
scaks/tests/correctors/thermodynamic_corrector_test.py
scaks/tests/models/__init__.py
scaks/tests/models/mkm_model_test.py
scaks/tests/models/models_tests.py
scaks/tests/parsers/__init__.py
scaks/tests/parsers/absolute_energy_parser_test.py
scaks/tests/parsers/chem_formula_test.py
scaks/tests/parsers/chem_state_test.py
scaks-0.1.0.dist-info/LICENSE
scaks-0.1.0.dist-info/METADATA
scaks-0.1.0.dist-info/WHEEL
scaks-0.1.0.dist-info/top_level.txt
scaks-0.1.0.dist-info/RECORD
