Metadata-Version: 2.1
Name: scaks
Version: 0.1.0
Summary: Micro-Kinetics Analysis package for Catalyst in Python
Home-page: UNKNOWN
Author: Shao-Zheng-Jiang
Author-email: shaozhengjiang@gmail.com
License: LICENSE
Platform: linux
Platform: macos
Requires-Dist: numpy
Requires-Dist: scipy
Requires-Dist: matplotlib
Requires-Dist: sympy
Requires-Dist: mpmath
Requires-Dist: mpi4py
Requires-Dist: prettytable
Requires-Dist: catplot
